sarscov2metaextract/__init__.py
sarscov2metaextract/cli.py
sarscov2_meta_extract-0.5.3.1.dist-info/LICENSE
sarscov2_meta_extract-0.5.3.1.dist-info/METADATA
sarscov2_meta_extract-0.5.3.1.dist-info/WHEEL
sarscov2_meta_extract-0.5.3.1.dist-info/entry_points.txt
sarscov2_meta_extract-0.5.3.1.dist-info/top_level.txt
sarscov2_meta_extract-0.5.3.1.dist-info/RECORD
