Metadata-Version: 2.1
Name: sarscov2-meta-extract
Version: 0.5.3.1
Summary: Extracts metadata from MSA for Galaxy workflow
Home-page: https://github.com/nickeener/sarscov2_meta_extract
Author: Nick Keener
Author-email: nickeener@gmail.com
License: UNKNOWN
Platform: UNKNOWN
Classifier: Programming Language :: Python :: 3
Classifier: License :: OSI Approved :: Academic Free License (AFL)
Classifier: Operating System :: OS Independent
Requires-Python: >=3.6
Requires-Dist: biopython
